hzh/__init__.py
hzh/pdf2txt.py
hzh-1.1.dist-info/License
hzh-1.1.dist-info/METADATA
hzh-1.1.dist-info/WHEEL
hzh-1.1.dist-info/top_level.txt
hzh-1.1.dist-info/RECORD
